Workbook

Sheet Dash
F1: =SUM(F3:F590) -> 13982440 | G1: =SUM(G3:G590) -> 336470.46 | H1: =SUM(H3:H590) -> 251380.3 | I1: =SUM(I3:I590) -> 5274.93
B2: Código da Empresa | C2: CNPJ | D2: Razão Social | E2: Procuração ativa? | F2: NF-e de Entrada (Autorizada) - SIGA | G2: NF-e de Entrada (Cancelada) - SIGA | H2: NF-e de Saída (Autorizada) - SIGA | I2: NF-e de Saída (Cancelada) - SIGA
B3: 3 | C3: 36.181.497/0001-39 | D3: ESTALEIRO BEBIDAS LTDA | E3: =IF(COUNTIF(Sheet3!E:E,Dash!B3)>0,"Sim","Não") -> Sim | F3: =SUMIFS('NF-e de Entrada'!E:E,'NF-e de Entrada'!A:A,Dash!B3,'NF-e de Entrada'!F:F,"Autorizada") -> 15148.5 | G3: =SUMIFS('NF-e de Entrada'!E:E,'NF-e de Entrada'!A:A,Dash!B3,'NF-e de Entrada'!F:F,"Cancelada") -> 0 | H3: =SUMIFS('NF-e de Saída'!E:E,'NF-e de Saída'!A:A,Dash!B3,'NF-e de Saída'!F:F,"AUTORIZADA") -> 0 | I3: =SUMIFS('NF-e de Saída'!E:E,'NF-e de Saída'!A:A,Dash!B3,'NF-e de Saída'!F:F,"CANCELADA") -> 0
B4: 5 | C4: 22.479.806/0001-47 | D4: A.H. DE FREITAS COSTA | E4: =IF(COUNTIF(Sheet3!E:E,Dash!B4)>0,"Sim","Não") -> Sim | F4: =SUMIFS('NF-e de Entrada'!E:E,'NF-e de Entrada'!A:A,Dash!B4,'NF-e de Entrada'!F:F,"Autorizada") -> 0 | G4: =SUMIFS('NF-e de Entrada'!E:E,'NF-e de Entrada'!A:A,Dash!B4,'NF-e de Entrada'!F:F,"Cancelada") -> 0 | H4: =SUMIFS('NF-e de Saída'!E:E,'NF-e de Saída'!A:A,Dash!B4,'NF-e de Saída'!F:F,"AUTORIZADA") -> 0 | I4: =SUMIFS('NF-e de Saída'!E:E,'NF-e de Saída'!A:A,Dash!B4,'NF-e de Saída'!F:F,"CANCELADA") -> 0
B5: 6 | C5: 42.077.510/0001-07 | D5: DEBITT CONTABILIDADE DIGITAL LTDA | E5: =IF(COUNTIF(Sheet3!E:E,Dash!B5)>0,"Sim","Não") -> Não | F5: =SUMIFS('NF-e de Entrada'!E:E,'NF-e de Entrada'!A:A,Dash!B5,'NF-e de Entrada'!F:F,"Autorizada") -> 0 | G5: =SUMIFS('NF-e de Entrada'!E:E,'NF-e de Entrada'!A:A,Dash!B5,'NF-e de Entrada'!F:F,"Cancelada") -> 0 | H5: =SUMIFS('NF-e de Saída'!E:E,'NF-e de Saída'!A:A,Dash!B5,'NF-e de Saída'!F:F,"AUTORIZADA") -> 0 | I5: =SUMIFS('NF-e de Saída'!E:E,'NF-e de Saída'!A:A,Dash!B5,'NF-e de Saída'!F:F,"CANCELADA") -> 0
B6: 9 | C6: 13.258.237/0001-19 | D6: NIPAN MASSAS CONGELADAS LTDA - ME. | E6: =IF(COUNTIF(Sheet3!E:E,Dash!B6)>0,"Sim","Não") -> Sim | F6: =SUMIFS('NF-e de Entrada'!E:E,'NF-e de Entrada'!A:A,Dash!B6,'NF-e de Entrada'!F:F,"Autorizada") -> 0 | G6: =SUMIFS('NF-e de Entrada'!E:E,'NF-e de Entrada'!A:A,Dash!B6,'NF-e de Entrada'!F:F,"Cancelada") -> 0 | H6: =SUMIFS('NF-e de Saída'!E:E,'NF-e de Saída'!A:A,Dash!B6,'NF-e de Saída'!F:F,"AUTORIZADA") -> 0 | I6: =SUMIFS('NF-e de Saída'!E:E,'NF-e de Saída'!A:A,Dash!B6,'NF-e de Saída'!F:F,"CANCELADA") -> 0
B7: 14 | C7: 07.516.056/0001-42 | D7: FRANCISCO DAS CHAGAS DE ALMEIDA BARROSO | E7: =IF(COUNTIF(Sheet3!E:E,Dash!B7)>0,"Sim","Não") -> Sim | F7: =SUMIFS('NF-e de Entrada'!E:E,'NF-e de Entrada'!A:A,Dash!B7,'NF-e de Entrada'!F:F,"Autorizada") -> 0 | G7: =SUMIFS('NF-e de Entrada'!E:E,'NF-e de Entrada'!A:A,Dash!B7,'NF-e de Entrada'!F:F,"Cancelada") -> 0 | H7: =SUMIFS('NF-e de Saída'!E:E,'NF-e de Saída'!A:A,Dash!B7,'NF-e de Saída'!F:F,"AUTORIZADA") -> 0 | I7: =SUMIFS('NF-e de Saída'!E:E,'NF-e de Saída'!A:A,Dash!B7,'NF-e de Saída'!F:F,"CANCELADA") -> 0
B8: 15 | C8: 00.169.175/0001-27 | D8: MARIA AURILENE DE SOUZA CAMURÇA ME | E8: =IF(COUNTIF(Sheet3!E:E,Dash!B8)>0,"Sim","Não") -> Não | F8: =SUMIFS('NF-e de Entrada'!E:E,'NF-e de Entrada'!A:A,Dash!B8,'NF-e de Entrada'!F:F,"Autorizada") -> 0 | G8: =SUMIFS('NF-e de Entrada'!E:E,'NF-e de Entrada'!A:A,Dash!B8,'NF-e de Entrada'!F:F,"Cancelada") -> 0 | H8: =SUMIFS('NF-e de Saída'!E:E,'NF-e de Saída'!A:A,Dash!B8,'NF-e de Saída'!F:F,"AUTORIZADA") -> 0 | I8: =SUMIFS('NF-e de Saída'!E:E,'NF-e de Saída'!A:A,Dash!B8,'NF-e de Saída'!F:F,"CANCELADA") -> 0
B9: 19 | C9: 36.410.673/0001-67 | D9: J P SILVA COMERCIO DE PRODUTOS FARMACEUTICOS | E9: =IF(COUNTIF(Sheet3!E:E,Dash!B9)>0,"Sim","Não") -> Sim | F9: =SUMIFS('NF-e de Entrada'!E:E,'NF-e de Entrada'!A:A,Dash!B9,'NF-e de Entrada'!F:F,"Autorizada") -> 0 | G9: =SUMIFS('NF-e de Entrada'!E:E,'NF-e de Entrada'!A:A,Dash!B9,'NF-e de Entrada'!F:F,"Cancelada") -> 0 | H9: =SUMIFS('NF-e de Saída'!E:E,'NF-e de Saída'!A:A,Dash!B9,'NF-e de Saída'!F:F,"AUTORIZADA") -> 0 | I9: =SUMIFS('NF-e de Saída'!E:E,'NF-e de Saída'!A:A,Dash!B9,'NF-e de Saída'!F:F,"CANCELADA") -> 0
B10: 21 | C10: 23.486.871/0001-62 | D10: FRANCISCO EVANILDO LIMA DA SILVA ME | E10: =IF(COUNTIF(Sheet3!E:E,Dash!B10)>0,"Sim","Não") -> Sim | F10: =SUMIFS('NF-e de Entrada'!E:E,'NF-e de Entrada'!A:A,Dash!B10,'NF-e de Entrada'!F:F,"Autorizada") -> 0 | G10: =SUMIFS('NF-e de Entrada'!E:E,'NF-e de Entrada'!A:A,Dash!B10,'NF-e de Entrada'!F:F,"Cancelada") -> 0 | H10: =SUMIFS('NF-e de Saída'!E:E,'NF-e de Saída'!A:A,Dash!B10,'NF-e de Saída'!F:F,"AUTORIZADA") -> 0 | I10: =SUMIFS('NF-e de Saída'!E:E,'NF-e de Saída'!A:A,Dash!B10,'NF-e de Saída'!F:F,"CANCELADA") -> 0
B11: 22 | C11: 20.743.516/0001-33 | D11: HOLANDA MAIA COMERCIO DE MEDICAMENTOS LTDA EPP | E11: =IF(COUNTIF(Sheet3!E:E,Dash!B11)>0,"Sim","Não") -> Sim | F11: =SUMIFS('NF-e de Entrada'!E:E,'NF-e de Entrada'!A:A,Dash!B11,'NF-e de Entrada'!F:F,"Autorizada") -> 29296.56 | G11: =SUMIFS('NF-e de Entrada'!E:E,'NF-e de Entrada'!A:A,Dash!B11,'NF-e de Entrada'!F:F,"Cancelada") -> 0 | H11: =SUMIFS('NF-e de Saída'!E:E,'NF-e de Saída'!A:A,Dash!B11,'NF-e de Saída'!F:F,"AUTORIZADA") -> 0 | I11: =SUMIFS('NF-e de Saída'!E:E,'NF-e de Saída'!A:A,Dash!B11,'NF-e de Saída'!F:F,"CANCELADA") -> 0
B12: 29 | C12: 18.452.941/0001-21 | D12: S B C INDUSTRIA E COMERCIO DE CONFECCOES E EQUIPAMENTOS LTDA. | E12: =IF(COUNTIF(Sheet3!E:E,Dash!B12)>0,"Sim","Não") -> Sim | F12: =SUMIFS('NF-e de Entrada'!E:E,'NF-e de Entrada'!A:A,Dash!B12,'NF-e de Entrada'!F:F,"Autorizada") -> 141969.28 | G12: =SUMIFS('NF-e de Entrada'!E:E,'NF-e de Entrada'!A:A,Dash!B12,'NF-e de Entrada'!F:F,"Cancelada") -> 0 | H12: =SUMIFS('NF-e de Saída'!E:E,'NF-e de Saída'!A:A,Dash!B12,'NF-e de Saída'!F:F,"AUTORIZADA") -> 0 | I12: =SUMIFS('NF-e de Saída'!E:E,'NF-e de Saída'!A:A,Dash!B12,'NF-e de Saída'!F:F,"CANCELADA") -> 0
B13: 31 | C13: 73.796.088/0001-73 | D13: REDE AMBIENTAL COMERCIO E SERVIÇOS LTDA | E13: =IF(COUNTIF(Sheet3!E:E,Dash!B13)>0,"Sim","Não") -> Não | F13: =SUMIFS('NF-e de Entrada'!E:E,'NF-e de Entrada'!A:A,Dash!B13,'NF-e de Entrada'!F:F,"Autorizada") -> 0 | G13: =SUMIFS('NF-e de Entrada'!E:E,'NF-e de Entrada'!A:A,Dash!B13,'NF-e de Entrada'!F:F,"Cancelada") -> 0 | H13: =SUMIFS('NF-e de Saída'!E:E,'NF-e de Saída'!A:A,Dash!B13,'NF-e de Saída'!F:F,"AUTORIZADA") -> 0 | I13: =SUMIFS('NF-e de Saída'!E:E,'NF-e de Saída'!A:A,Dash!B13,'NF-e de Saída'!F:F,"CANCELADA") -> 0
B14: 33 | C14: 10.463.419/0001-33 | D14: MARQUES PET SHOP LTDA | E14: =IF(COUNTIF(Sheet3!E:E,Dash!B14)>0,"Sim","Não") -> Sim | F14: =SUMIFS('NF-e de Entrada'!E:E,'NF-e de Entrada'!A:A,Dash!B14,'NF-e de Entrada'!F:F,"Autorizada") -> 1537.77 | G14: =SUMIFS('NF-e de Entrada'!E:E,'NF-e de Entrada'!A:A,Dash!B14,'NF-e de Entrada'!F:F,"Cancelada") -> 0 | H14: =SUMIFS('NF-e de Saída'!E:E,'NF-e de Saída'!A:A,Dash!B14,'NF-e de Saída'!F:F,"AUTORIZADA") -> 0 | I14: =SUMIFS('NF-e de Saída'!E:E,'NF-e de Saída'!A:A,Dash!B14,'NF-e de Saída'!F:F,"CANCELADA") -> 0
... B590: 900 | C590: 67.564.528/0001-64 | D590: SARAH E RUBIA ODONTOLOGIA INTEGRADA LTDA | E590: =IF(COUNTIF(Sheet3!E:E,Dash!B590)>0,"Sim","Não") -> Não | F590: =SUMIFS('NF-e de Entrada'!E:E,'NF-e de Entrada'!A:A,Dash!B590,'NF-e de Entrada'!F:F,"Autorizada") -> 0 | G590: =SUMIFS('NF-e de Entrada'!E:E,'NF-e de Entrada'!A:A,Dash!B590,'NF-e de Entrada'!F:F,"Cancelada") -> 0 | H590: =SUMIFS('NF-e de Saída'!E:E,'NF-e de Saída'!A:A,Dash!B590,'NF-e de Saída'!F:F,"AUTORIZADA") -> 0 | I590: =SUMIFS('NF-e de Saída'!E:E,'NF-e de Saída'!A:A,Dash!B590,'NF-e de Saída'!F:F,"CANCELADA") -> 0

Sheet NF-e de Entrada
A1: Código Domínio | B1: CNPJ | C1: Numero | D1: Chave de Acesso | E1: Número | F1: Status | G1: Tipo | H1: Data
A2: 154 | B2: 12981026000147 | C2: 2657600 | D2: 23260663360234000160550010026576001238812342 | E2: 5762.19 | F2: AUTORIZADA | G2: INTERNO | H2: 2026-06-01
A3: 154 | B3: 12981026000147 | C3: 1232 | D3: 23260615309004000123550010000012321691423897 | E3: 6834.04 | F3: AUTORIZADA | G3: INTERNO | H3: 2026-06-01
A4: 154 | B4: 12981026000147 | C4: 24906 | D4: 23260603616846000149550020000249061000312834 | E4: 627 | F4: AUTORIZADA | G4: INTERNO | H4: 2026-06-01
A5: 154 | B5: 12981026000147 | C5: 89864 | D5: 23260609035933000199550010000898641411674400 | E5: 1459.1 | F5: AUTORIZADA | G5: INTERNO | H5: 2026-06-01
A6: 154 | B6: 12981026000147 | C6: 3004 | D6: 23260657337442000145550010000030041490030498 | E6: 292.82 | F6: AUTORIZADA | G6: INTERNO | H6: 2026-06-01
A7: 154 | B7: 12981026000147 | C7: 14626 | D7: 23260612981026000309550010000146261000273215 | E7: 77.08 | F7: AUTORIZADA | G7: INTERNO | H7: 2026-06-01
A8: 154 | B8: 12981026000147 | C8: 1622 | D8: 23260629080327000100551110000016221006148322 | E8: 1071.4 | F8: AUTORIZADA | G8: INTERNO | H8: 2026-06-01
A9: 154 | B9: 12981026000147 | C9: 1711 | D9: 23260626270614000187550010000017111295067336 | E9: 996.98 | F9: AUTORIZADA | G9: INTERNO | H9: 2026-06-01
A10: 154 | B10: 12981026000147 | C10: 180753 | D10: 23260603623218000271550030001807531216795817 | E10: 3324 | F10: AUTORIZADA | G10: INTERNO | H10: 2026-06-01
A11: 154 | B11: 12981026000147 | C11: 1327819 | D11: 23260605139918000130550000013278191168104498 | E11: 101.2 | F11: AUTORIZADA | G11: INTERNO | H11: 2026-06-01
A12: 154 | B12: 12981026000147 | C12: 1327818 | D12: 23260605139918000130550000013278181232147434 | E12: 567.86 | F12: AUTORIZADA | G12: INTERNO | H12: 2026-06-01
A13: 154 | B13: 12981026000147 | C13: 723607 | D13: 23260635229640000152550010007236071755764446 | E13: 1180.54 | F13: AUTORIZADA | G13: INTERNO | H13: 2026-06-01
... A2763: 836 | B2763: 36965599000145 | C2763: 5198388 | D2763: 23260623577851000105550010051983881791651916 | E2763: 317.18 | F2763: AUTORIZADA | G2763: INTERNO | H2763: 2026-06-01

Sheet NF-e de Saída
A1: Source.Name.3 | B1: cnpj | C1: numDocumentoFiscal | D1: chaveAcesso | E1: vlrDocumento | F1: resultadoProcessamento | G1: datReferencia
A2: 204 | B2: 33384059000180 | C2: 354 | D2: 23260633384059000180550030000003541015160962 | E2: 336.4 | F2: AUTORIZADA | G2: 2026-06-01
A3: 204 | B3: 33384059000180 | C3: 355 | D3: 23260633384059000180550030000003551814000939 | E3: 610.1 | F3: AUTORIZADA | G3: 2026-06-01
A4: 204 | B4: 33384059000180 | C4: 356 | D4: 23260633384059000180550030000003561330155214 | E4: 491.53 | F4: AUTORIZADA | G4: 2026-06-01
A5: 204 | B5: 33384059000180 | C5: 357 | D5: 23260633384059000180550030000003571513498550 | E5: 2364.93 | F5: CANCELADA | G5: 2026-06-01
A6: 204 | B6: 33384059000180 | C6: 358 | D6: 23260633384059000180550030000003581457146700 | E6: 652.74 | F6: AUTORIZADA | G6: 2026-06-01
A7: 204 | B7: 33384059000180 | C7: 359 | D7: 23260633384059000180550030000003591360282305 | E7: 1511.1 | F7: AUTORIZADA | G7: 2026-06-01
A8: 204 | B8: 33384059000180 | C8: 360 | D8: 23260633384059000180550030000003601731803724 | E8: 318.4 | F8: AUTORIZADA | G8: 2026-06-01
A9: 204 | B9: 33384059000180 | C9: 361 | D9: 23260633384059000180550030000003611623877817 | E9: 1546.9 | F9: AUTORIZADA | G9: 2026-06-01
A10: 204 | B10: 33384059000180 | C10: 362 | D10: 23260633384059000180550030000003621495597857 | E10: 1747.42 | F10: AUTORIZADA | G10: 2026-06-01
A11: 426 | B11: 32084111000110 | C11: 367 | D11: 23260632084111000110550020000003671951496868 | E11: 372.26 | F11: AUTORIZADA | G11: 2026-06-01
A12: 426 | B12: 32084111000110 | C12: 368 | D12: 23260632084111000110550020000003681476627751 | E12: 303.61 | F12: AUTORIZADA | G12: 2026-06-01
A13: 426 | B13: 32084111000110 | C13: 369 | D13: 23260632084111000110550020000003691231255344 | E13: 572.39 | F13: AUTORIZADA | G13: 2026-06-01
... A324: 517 | B324: 33912498000118 | C324: 1164 | D324: 23260633912498000118550010000011641402008323 | E324: 10350 | F324: AUTORIZADA | G324: 2026-06-01

Sheet Sheet3
A1: cnpj | B1: cgf | C1: razaoSocial | D1: regime | E1: cadastro_dominio
A2: 15122739000143 | B2: 65974123 | C2: FORTVISION COMERCIO DE PRODUTOS OPTICOS LTDA | D2: MICROEMPRESA | E2: 257
A3: 33384059000180 | B3: 69359202 | C3: J. L. E. DE OLIVEIRA SR PANDINHA | D3: MICROEMPRESA | E3: 204
A4: 20951181000149 | B4: 63483297 | C4: ADE COMERCIO DE CALCADOS LTDA | D4: NORMAL | E4: 482
A5: 33912498000118 | B5: 69551715 | C5: MASTER CAIXAS EMBALAGENS LTDA | D5: NORMAL | E5: 517
A6: 33912498000118 | B6: 69551715 | C6: MASTER CAIXAS EMBALAGENS LTDA | D6: NORMAL | E6: 517
A7: 32084111000110 | B7: 67915841 | C7: OCULART OTICA LTDA | D7: EPP | E7: 426
A8: 22850504000133 | B8: 64710580 | C8: CARIRI COMÃ‰RCIO DE ARTIGOS OPTICOS LTDA. - ME | D8: EPP | E8: 612
A9: 32343397000100 | B9: 67940188 | C9: LIBERTY JEANS LTDA | D9: NORMAL | E9: 149
A10: 36220012000179 | B10: 62507168 | C10: UAU CAFETERIA LTDA | D10: MICROEMPRESA | E10: 235
A11: 20951181000491 | B11: 67364829 | C11: ADE COMERCIO DE CALCADOS LTDA | D11: NORMAL | E11: 485
A12: 20373830000171 | B12: 63350661 | C12: OBA FESTAS LTDA | D12: NORMAL | E12: 445
A13: 03854920000165 | B13: 62993950 | C13: S & A COMERCIO DE ARTIGOS OPTICOS LTDA ME | D13: EPP | E13: 619
... A308: 32084111000110 | B308: 67915841 | C308: OCULART OTICA LTDA | D308: EPP | E308: 426
